setup.cfg
setup.py
TodoFlow.egg-info/SOURCES.txt
Todoflow.egg-info/PKG-INFO
Todoflow.egg-info/SOURCES.txt
Todoflow.egg-info/dependency_links.txt
Todoflow.egg-info/top_level.txt
todoflow/__init__.py
todoflow/compatibility.py
todoflow/lexer.py
todoflow/parse_date.py
todoflow/parser.py
todoflow/query.py
todoflow/query_lexer.py
todoflow/query_parser.py
todoflow/textutils.py
todoflow/todoitem.py
todoflow/todos.py