Metadata-Version: 1.0
Name: TodoFlow
Version: 5.0.0
Summary: taskpaper in python
Home-page: https://github.com/bevesce/TodoFlow
Author: Piotr Wilczyński
Author-email: wilczynski.pi@gmail.com
License: UNKNOWN
Platform: UNKNOWN
